{
  "rasa_nlu_data": {
    "common_examples": [
      {
        "entities": [
          {
            "end": 7,
            "entity": "system",
            "start": 5,
            "value": "系统"
          }
        ],
        "intent": "get_alarm_in_system",
        "text": "今天哪一些系统存在报警信息呢"
      },
      {
        "entities": [
          {
            "end": 6,
            "entity": "system",
            "start": 4,
            "value": "系统"
          }
        ],
        "intent": "get_alarm_in_system",
        "text": "今天哪个系统报出过报警信号"
      },
      {
        "entities": [
          {
            "end": 6,
            "entity": "system",
            "start": 4,
            "value": "系统"
          }
        ],
        "intent": "get_alarm_in_system",
        "text": "今天哪个系统有过告警信号"
      },
      {
        "entities": [
          {
            "end": 6,
            "entity": "system",
            "start": 4,
            "value": "平台"
          }
        ],
        "intent": "get_alarm_in_system",
        "text": "今天哪些平台有报警呀"
      },
      {
        "entities": [
          {
            "end": 6,
            "entity": "system",
            "start": 4,
            "value": "平台"
          }
        ],
        "intent": "get_alarm_in_system",
        "text": "今天哪些平台有过警告啊"
      },
      {
        "entities": [
          {
            "end": 8,
            "entity": "system",
            "start": 6,
            "value": "系统"
          }
        ],
        "intent": "get_alarm_in_system",
        "text": "今天存不存在系统存在告警信号呀"
      },
      {
        "entities": [
          {
            "end": 9,
            "entity": "system",
            "start": 7,
            "value": "平台"
          }
        ],
        "intent": "get_alarm_in_system",
        "text": "告诉我今天哪些平台有过告警信息呀"
      },
      {
        "entities": [
          {
            "end": 11,
            "entity": "system",
            "start": 9,
            "value": "平台"
          }
        ],
        "intent": "get_alarm_in_system",
        "text": "告诉我今天存不存在平台存在过报警信息"
      },
      {
        "entities": [
          {
            "end": 7,
            "entity": "system",
            "start": 5,
            "value": "平台"
          }
        ],
        "intent": "get_alarm_in_system",
        "text": "告诉我哪个平台出现过警告呢"
      },
      {
        "entities": [
          {
            "end": 7,
            "entity": "system",
            "start": 5,
            "value": "平台"
          }
        ],
        "intent": "get_alarm_in_system",
        "text": "告诉我哪个平台报出过报警"
      },
      {
        "entities": [
          {
            "end": 7,
            "entity": "system",
            "start": 5,
            "value": "平台"
          }
        ],
        "intent": "get_alarm_in_system",
        "text": "告诉我哪个平台有过告警信息呢"
      },
      {
        "entities": [
          {
            "end": 7,
            "entity": "system",
            "start": 5,
            "value": "系统"
          }
        ],
        "intent": "get_alarm_in_system",
        "text": "告诉我哪个系统存在告警啊"
      },
      {
        "entities": [
          {
            "end": 7,
            "entity": "system",
            "start": 5,
            "value": "系统"
          }
        ],
        "intent": "get_alarm_in_system",
        "text": "告诉我哪个系统报出过告警信号"
      },
      {
        "entities": [
          {
            "end": 7,
            "entity": "system",
            "start": 5,
            "value": "系统"
          }
        ],
        "intent": "get_alarm_in_system",
        "text": "告诉我哪些系统出现告警"
      },
      {
        "entities": [
          {
            "end": 7,
            "entity": "system",
            "start": 5,
            "value": "系统"
          }
        ],
        "intent": "get_alarm_in_system",
        "text": "告诉我哪些系统存在警告"
      },
      {
        "entities": [
          {
            "end": 9,
            "entity": "system",
            "start": 7,
            "value": "平台"
          }
        ],
        "intent": "get_alarm_in_system",
        "text": "告诉我存不存在平台报出报警信号"
      },
      {
        "entities": [
          {
            "end": 9,
            "entity": "system",
            "start": 7,
            "value": "平台"
          }
        ],
        "intent": "get_alarm_in_system",
        "text": "告诉我存不存在平台报出过告警信号"
      },
      {
        "entities": [
          {
            "end": 9,
            "entity": "system",
            "start": 7,
            "value": "系统"
          }
        ],
        "intent": "get_alarm_in_system",
        "text": "告诉我存不存在系统存在过告警信号啊"
      },
      {
        "entities": [
          {
            "end": 9,
            "entity": "system",
            "start": 7,
            "value": "系统"
          }
        ],
        "intent": "get_alarm_in_system",
        "text": "告诉我最近哪个系统出现告警"
      },
      {
        "entities": [
          {
            "end": 10,
            "entity": "system",
            "start": 8,
            "value": "平台"
          }
        ],
        "intent": "get_alarm_in_system",
        "text": "告诉我最近有没有平台有报警信息"
      },
      {
        "entities": [
          {
            "end": 11,
            "entity": "system",
            "start": 9,
            "value": "平台"
          }
        ],
        "intent": "get_alarm_in_system",
        "text": "告诉我这个时候哪个平台出现警告信息"
      },
      {
        "entities": [
          {
            "end": 13,
            "entity": "system",
            "start": 11,
            "value": "平台"
          }
        ],
        "intent": "get_alarm_in_system",
        "text": "告诉我这个时候存不存在平台有警告啊"
      },
      {
        "entities": [
          {
            "end": 9,
            "entity": "system",
            "start": 7,
            "value": "平台"
          }
        ],
        "intent": "get_alarm_in_system",
        "text": "告诉我这会哪个平台报出警告"
      },
      {
        "entities": [
          {
            "end": 4,
            "entity": "system",
            "start": 2,
            "value": "平台"
          }
        ],
        "intent": "get_alarm_in_system",
        "text": "哪个平台出现报警信号"
      },
      {
        "entities": [
          {
            "end": 4,
            "entity": "system",
            "start": 2,
            "value": "系统"
          }
        ],
        "intent": "get_alarm_in_system",
        "text": "哪个系统出现告警呢"
      },
      {
        "entities": [
          {
            "end": 4,
            "entity": "system",
            "start": 2,
            "value": "系统"
          }
        ],
        "intent": "get_alarm_in_system",
        "text": "哪个系统出现过告警"
      },
      {
        "entities": [
          {
            "end": 4,
            "entity": "system",
            "start": 2,
            "value": "系统"
          }
        ],
        "intent": "get_alarm_in_system",
        "text": "哪个系统存在告警啊"
      },
      {
        "entities": [
          {
            "end": 4,
            "entity": "system",
            "start": 2,
            "value": "系统"
          }
        ],
        "intent": "get_alarm_in_system",
        "text": "哪个系统报出警告啊"
      },
      {
        "entities": [
          {
            "end": 4,
            "entity": "system",
            "start": 2,
            "value": "平台"
          }
        ],
        "intent": "get_alarm_in_system",
        "text": "哪些平台出现告警信息"
      },
      {
        "entities": [
          {
            "end": 4,
            "entity": "system",
            "start": 2,
            "value": "系统"
          }
        ],
        "intent": "get_alarm_in_system",
        "text": "哪些系统存在警告信息呢"
      },
      {
        "entities": [
          {
            "end": 4,
            "entity": "system",
            "start": 2,
            "value": "系统"
          }
        ],
        "intent": "get_alarm_in_system",
        "text": "哪些系统存在过警告信息呀"
      },
      {
        "entities": [
          {
            "end": 6,
            "entity": "system",
            "start": 4,
            "value": "平台"
          }
        ],
        "intent": "get_alarm_in_system",
        "text": "存不存在平台出现过告警信号啊"
      },
      {
        "entities": [
          {
            "end": 6,
            "entity": "system",
            "start": 4,
            "value": "平台"
          }
        ],
        "intent": "get_alarm_in_system",
        "text": "存不存在平台有警告信息"
      },
      {
        "entities": [
          {
            "end": 6,
            "entity": "system",
            "start": 4,
            "value": "平台"
          }
        ],
        "intent": "get_alarm_in_system",
        "text": "存不存在平台有过报警啊"
      },
      {
        "entities": [
          {
            "end": 6,
            "entity": "system",
            "start": 4,
            "value": "系统"
          }
        ],
        "intent": "get_alarm_in_system",
        "text": "存不存在系统出现告警信号"
      },
      {
        "entities": [
          {
            "end": 6,
            "entity": "system",
            "start": 4,
            "value": "系统"
          }
        ],
        "intent": "get_alarm_in_system",
        "text": "存不存在系统出现过报警呢"
      },
      {
        "entities": [
          {
            "end": 6,
            "entity": "system",
            "start": 4,
            "value": "系统"
          }
        ],
        "intent": "get_alarm_in_system",
        "text": "存不存在系统出现过警告信号"
      },
      {
        "entities": [
          {
            "end": 6,
            "entity": "system",
            "start": 4,
            "value": "系统"
          }
        ],
        "intent": "get_alarm_in_system",
        "text": "存不存在系统存在警告啊"
      },
      {
        "entities": [
          {
            "end": 6,
            "entity": "system",
            "start": 4,
            "value": "系统"
          }
        ],
        "intent": "get_alarm_in_system",
        "text": "存不存在系统报出过报警信号呀"
      },
      {
        "entities": [
          {
            "end": 6,
            "entity": "system",
            "start": 4,
            "value": "系统"
          }
        ],
        "intent": "get_alarm_in_system",
        "text": "存不存在系统有报警信号"
      },
      {
        "entities": [
          {
            "end": 7,
            "entity": "system",
            "start": 5,
            "value": "系统"
          }
        ],
        "intent": "get_alarm_in_system",
        "text": "最近哪一些系统报出告警信息呀"
      },
      {
        "entities": [
          {
            "end": 6,
            "entity": "system",
            "start": 4,
            "value": "系统"
          }
        ],
        "intent": "get_alarm_in_system",
        "text": "最近哪些系统出现过报警信息"
      },
      {
        "entities": [
          {
            "end": 6,
            "entity": "system",
            "start": 4,
            "value": "系统"
          }
        ],
        "intent": "get_alarm_in_system",
        "text": "最近哪些系统存在告警呀"
      },
      {
        "entities": [
          {
            "end": 8,
            "entity": "system",
            "start": 6,
            "value": "平台"
          }
        ],
        "intent": "get_alarm_in_system",
        "text": "最近存不存在平台存在过告警信息啊"
      },
      {
        "entities": [
          {
            "end": 7,
            "entity": "system",
            "start": 5,
            "value": "系统"
          }
        ],
        "intent": "get_alarm_in_system",
        "text": "最近有没有系统报出过警告信号啊"
      },
      {
        "entities": [
          {
            "end": 5,
            "entity": "system",
            "start": 3,
            "value": "平台"
          }
        ],
        "intent": "get_alarm_in_system",
        "text": "有没有平台出现报警信息"
      },
      {
        "entities": [
          {
            "end": 5,
            "entity": "system",
            "start": 3,
            "value": "平台"
          }
        ],
        "intent": "get_alarm_in_system",
        "text": "有没有平台出现过报警信号"
      },
      {
        "entities": [
          {
            "end": 5,
            "entity": "system",
            "start": 3,
            "value": "系统"
          }
        ],
        "intent": "get_alarm_in_system",
        "text": "有没有系统出现警告信息啊"
      },
      {
        "entities": [
          {
            "end": 5,
            "entity": "system",
            "start": 3,
            "value": "系统"
          }
        ],
        "intent": "get_alarm_in_system",
        "text": "有没有系统存在报警"
      },
      {
        "entities": [
          {
            "end": 5,
            "entity": "system",
            "start": 3,
            "value": "系统"
          }
        ],
        "intent": "get_alarm_in_system",
        "text": "有没有系统报出过告警呀"
      },
      {
        "entities": [
          {
            "end": 5,
            "entity": "system",
            "start": 3,
            "value": "系统"
          }
        ],
        "intent": "get_alarm_in_system",
        "text": "有没有系统有报警呢"
      },
      {
        "entities": [
          {
            "end": 7,
            "entity": "system",
            "start": 5,
            "value": "平台"
          }
        ],
        "intent": "get_alarm_in_system",
        "text": "现在哪一些平台有过报警信息呀"
      },
      {
        "entities": [
          {
            "end": 7,
            "entity": "system",
            "start": 5,
            "value": "系统"
          }
        ],
        "intent": "get_alarm_in_system",
        "text": "现在哪一些系统报出报警"
      },
      {
        "entities": [
          {
            "end": 7,
            "entity": "system",
            "start": 5,
            "value": "系统"
          }
        ],
        "intent": "get_alarm_in_system",
        "text": "现在哪一些系统有告警"
      },
      {
        "entities": [
          {
            "end": 6,
            "entity": "system",
            "start": 4,
            "value": "平台"
          }
        ],
        "intent": "get_alarm_in_system",
        "text": "现在哪个平台有过报警信号呢"
      },
      {
        "entities": [
          {
            "end": 6,
            "entity": "system",
            "start": 4,
            "value": "系统"
          }
        ],
        "intent": "get_alarm_in_system",
        "text": "现在哪个系统出现过报警呀"
      },
      {
        "entities": [
          {
            "end": 8,
            "entity": "system",
            "start": 6,
            "value": "系统"
          }
        ],
        "intent": "get_alarm_in_system",
        "text": "现在存不存在系统出现过报警"
      },
      {
        "entities": [
          {
            "end": 8,
            "entity": "system",
            "start": 6,
            "value": "系统"
          }
        ],
        "intent": "get_alarm_in_system",
        "text": "说下今天哪个系统出现报警"
      },
      {
        "entities": [
          {
            "end": 8,
            "entity": "system",
            "start": 6,
            "value": "系统"
          }
        ],
        "intent": "get_alarm_in_system",
        "text": "说下今天哪个系统有过告警"
      },
      {
        "entities": [
          {
            "end": 7,
            "entity": "system",
            "start": 5,
            "value": "平台"
          }
        ],
        "intent": "get_alarm_in_system",
        "text": "说下哪一些平台存在过告警"
      },
      {
        "entities": [
          {
            "end": 7,
            "entity": "system",
            "start": 5,
            "value": "系统"
          }
        ],
        "intent": "get_alarm_in_system",
        "text": "说下哪一些系统有过报警信息呢"
      },
      {
        "entities": [
          {
            "end": 6,
            "entity": "system",
            "start": 4,
            "value": "平台"
          }
        ],
        "intent": "get_alarm_in_system",
        "text": "说下哪个平台出现过报警信息呀"
      },
      {
        "entities": [
          {
            "end": 6,
            "entity": "system",
            "start": 4,
            "value": "平台"
          }
        ],
        "intent": "get_alarm_in_system",
        "text": "说下哪个平台报出告警"
      },
      {
        "entities": [
          {
            "end": 6,
            "entity": "system",
            "start": 4,
            "value": "平台"
          }
        ],
        "intent": "get_alarm_in_system",
        "text": "说下哪些平台报出告警呀"
      },
      {
        "entities": [
          {
            "end": 8,
            "entity": "system",
            "start": 6,
            "value": "系统"
          }
        ],
        "intent": "get_alarm_in_system",
        "text": "说下存不存在系统报出报警"
      },
      {
        "entities": [
          {
            "end": 8,
            "entity": "system",
            "start": 6,
            "value": "系统"
          }
        ],
        "intent": "get_alarm_in_system",
        "text": "说下存不存在系统报出过告警啊"
      },
      {
        "entities": [
          {
            "end": 8,
            "entity": "system",
            "start": 6,
            "value": "系统"
          }
        ],
        "intent": "get_alarm_in_system",
        "text": "说下存不存在系统报出过报警呢"
      },
      {
        "entities": [
          {
            "end": 8,
            "entity": "system",
            "start": 6,
            "value": "系统"
          }
        ],
        "intent": "get_alarm_in_system",
        "text": "说下存不存在系统有报警信息"
      },
      {
        "entities": [
          {
            "end": 8,
            "entity": "system",
            "start": 6,
            "value": "系统"
          }
        ],
        "intent": "get_alarm_in_system",
        "text": "说下存不存在系统有报警呀"
      },
      {
        "entities": [
          {
            "end": 8,
            "entity": "system",
            "start": 6,
            "value": "系统"
          }
        ],
        "intent": "get_alarm_in_system",
        "text": "说下存不存在系统有过报警呢"
      },
      {
        "entities": [
          {
            "end": 9,
            "entity": "system",
            "start": 7,
            "value": "平台"
          }
        ],
        "intent": "get_alarm_in_system",
        "text": "说下最近哪一些平台报出报警呀"
      },
      {
        "entities": [
          {
            "end": 7,
            "entity": "system",
            "start": 5,
            "value": "平台"
          }
        ],
        "intent": "get_alarm_in_system",
        "text": "说下有没有平台有过警告呢"
      },
      {
        "entities": [
          {
            "end": 7,
            "entity": "system",
            "start": 5,
            "value": "系统"
          }
        ],
        "intent": "get_alarm_in_system",
        "text": "说下有没有系统报出告警"
      },
      {
        "entities": [
          {
            "end": 8,
            "entity": "system",
            "start": 6,
            "value": "系统"
          }
        ],
        "intent": "get_alarm_in_system",
        "text": "说下现在哪个系统有过报警信息"
      },
      {
        "entities": [
          {
            "end": 8,
            "entity": "system",
            "start": 6,
            "value": "平台"
          }
        ],
        "intent": "get_alarm_in_system",
        "text": "说下现在哪些平台报出告警啊"
      },
      {
        "entities": [
          {
            "end": 10,
            "entity": "system",
            "start": 8,
            "value": "平台"
          }
        ],
        "intent": "get_alarm_in_system",
        "text": "说下现在存不存在平台存在告警信号"
      },
      {
        "entities": [
          {
            "end": 9,
            "entity": "system",
            "start": 7,
            "value": "平台"
          }
        ],
        "intent": "get_alarm_in_system",
        "text": "说下现在有没有平台存在告警呀"
      },
      {
        "entities": [
          {
            "end": 12,
            "entity": "system",
            "start": 10,
            "value": "平台"
          }
        ],
        "intent": "get_alarm_in_system",
        "text": "说下这个时候存不存在平台出现过报警信息呀"
      },
      {
        "entities": [
          {
            "end": 12,
            "entity": "system",
            "start": 10,
            "value": "系统"
          }
        ],
        "intent": "get_alarm_in_system",
        "text": "说下这个时候存不存在系统存在报警"
      },
      {
        "entities": [
          {
            "end": 11,
            "entity": "system",
            "start": 9,
            "value": "平台"
          }
        ],
        "intent": "get_alarm_in_system",
        "text": "说下这个时候有没有平台有过警告呀"
      },
      {
        "entities": [
          {
            "end": 9,
            "entity": "system",
            "start": 7,
            "value": "平台"
          }
        ],
        "intent": "get_alarm_in_system",
        "text": "说下这会哪一些平台存在警告啊"
      },
      {
        "entities": [
          {
            "end": 8,
            "entity": "system",
            "start": 6,
            "value": "系统"
          }
        ],
        "intent": "get_alarm_in_system",
        "text": "说下这会哪个系统存在警告信息"
      },
      {
        "entities": [
          {
            "end": 10,
            "entity": "system",
            "start": 8,
            "value": "系统"
          }
        ],
        "intent": "get_alarm_in_system",
        "text": "说下这会存不存在系统出现过告警信息"
      },
      {
        "entities": [
          {
            "end": 9,
            "entity": "system",
            "start": 7,
            "value": "平台"
          }
        ],
        "intent": "get_alarm_in_system",
        "text": "说下这会有没有平台出现过告警"
      },
      {
        "entities": [
          {
            "end": 8,
            "entity": "system",
            "start": 6,
            "value": "平台"
          }
        ],
        "intent": "get_alarm_in_system",
        "text": "这个时候哪个平台出现过警告信息呢"
      },
      {
        "entities": [
          {
            "end": 8,
            "entity": "system",
            "start": 6,
            "value": "平台"
          }
        ],
        "intent": "get_alarm_in_system",
        "text": "这个时候哪些平台有过报警"
      },
      {
        "entities": [
          {
            "end": 10,
            "entity": "system",
            "start": 8,
            "value": "平台"
          }
        ],
        "intent": "get_alarm_in_system",
        "text": "这个时候存不存在平台存在告警呢"
      },
      {
        "entities": [
          {
            "end": 10,
            "entity": "system",
            "start": 8,
            "value": "平台"
          }
        ],
        "intent": "get_alarm_in_system",
        "text": "这个时候存不存在平台有告警信息"
      },
      {
        "entities": [
          {
            "end": 10,
            "entity": "system",
            "start": 8,
            "value": "平台"
          }
        ],
        "intent": "get_alarm_in_system",
        "text": "这个时候存不存在平台有告警呀"
      },
      {
        "entities": [
          {
            "end": 10,
            "entity": "system",
            "start": 8,
            "value": "系统"
          }
        ],
        "intent": "get_alarm_in_system",
        "text": "这个时候存不存在系统报出告警呢"
      },
      {
        "entities": [
          {
            "end": 10,
            "entity": "system",
            "start": 8,
            "value": "系统"
          }
        ],
        "intent": "get_alarm_in_system",
        "text": "这个时候存不存在系统报出报警"
      },
      {
        "entities": [
          {
            "end": 10,
            "entity": "system",
            "start": 8,
            "value": "系统"
          }
        ],
        "intent": "get_alarm_in_system",
        "text": "这个时候存不存在系统报出过告警信号啊"
      },
      {
        "entities": [
          {
            "end": 9,
            "entity": "system",
            "start": 7,
            "value": "平台"
          }
        ],
        "intent": "get_alarm_in_system",
        "text": "这个时候有没有平台存在过警告"
      },
      {
        "entities": [
          {
            "end": 9,
            "entity": "system",
            "start": 7,
            "value": "系统"
          }
        ],
        "intent": "get_alarm_in_system",
        "text": "这个时候有没有系统出现过警告"
      },
      {
        "entities": [
          {
            "end": 9,
            "entity": "system",
            "start": 7,
            "value": "系统"
          }
        ],
        "intent": "get_alarm_in_system",
        "text": "这个时候有没有系统报出警告"
      },
      {
        "entities": [
          {
            "end": 7,
            "entity": "system",
            "start": 5,
            "value": "系统"
          }
        ],
        "intent": "get_alarm_in_system",
        "text": "这会哪一些系统报出警告呢"
      },
      {
        "entities": [
          {
            "end": 7,
            "entity": "system",
            "start": 5,
            "value": "平台"
          }
        ],
        "intent": "get_alarm_in_system",
        "text": "这会有没有平台出现过告警信息呀"
      },
      {
        "entities": [
          {
            "end": 7,
            "entity": "system",
            "start": 5,
            "value": "平台"
          }
        ],
        "intent": "get_alarm_in_system",
        "text": "这会有没有平台报出报警信号"
      },
      {
        "entities": [
          {
            "end": 7,
            "entity": "system",
            "start": 5,
            "value": "系统"
          }
        ],
        "intent": "get_alarm_in_system",
        "text": "这会有没有系统存在报警呀"
      },
      {
        "entities": [
          {
            "end": 7,
            "entity": "system",
            "start": 5,
            "value": "系统"
          }
        ],
        "intent": "get_alarm_in_system",
        "text": "这会有没有系统有过警告信息"
      },
      {
        "entities": [
          {
            "end": 7,
            "entity": "system",
            "start": 0,
            "value": "华为大数据平台"
          }
        ],
        "intent": "get_people_in_system",
        "text": "华为大数据平台的主管人"
      },
      {
        "entities": [
          {
            "end": 7,
            "entity": "system",
            "start": 0,
            "value": "华为大数据平台"
          }
        ],
        "intent": "get_people_in_system",
        "text": "华为大数据平台的主管者"
      },
      {
        "entities": [
          {
            "end": 7,
            "entity": "system",
            "start": 0,
            "value": "华为大数据平台"
          }
        ],
        "intent": "get_people_in_system",
        "text": "华为大数据平台的联系人"
      },
      {
        "entities": [
          {
            "end": 7,
            "entity": "system",
            "start": 0,
            "value": "华为大数据平台"
          }
        ],
        "intent": "get_people_in_system",
        "text": "华为大数据平台联系者"
      },
      {
        "entities": [
          {
            "end": 7,
            "entity": "system",
            "start": 0,
            "value": "华为大数据平台"
          }
        ],
        "intent": "get_people_in_system",
        "text": "华为大数据平台负责者是谁"
      },
      {
        "entities": [
          {
            "end": 10,
            "entity": "system",
            "start": 3,
            "value": "华为大数据平台"
          }
        ],
        "intent": "get_people_in_system",
        "text": "告诉我华为大数据平台主管者是谁呀"
      },
      {
        "entities": [
          {
            "end": 10,
            "entity": "system",
            "start": 3,
            "value": "华为大数据平台"
          }
        ],
        "intent": "get_people_in_system",
        "text": "告诉我华为大数据平台的负责人"
      },
      {
        "entities": [
          {
            "end": 10,
            "entity": "system",
            "start": 3,
            "value": "华为大数据平台"
          }
        ],
        "intent": "get_people_in_system",
        "text": "告诉我华为大数据平台负责人是哪位"
      },
      {
        "entities": [
          {
            "end": 10,
            "entity": "system",
            "start": 3,
            "value": "华为大数据平台"
          }
        ],
        "intent": "get_people_in_system",
        "text": "告诉我华为大数据平台负责者"
      },
      {
        "entities": [
          {
            "end": 9,
            "entity": "system",
            "start": 3,
            "value": "基础资源平台"
          }
        ],
        "intent": "get_people_in_system",
        "text": "告诉我基础资源平台联系者"
      },
      {
        "entities": [
          {
            "end": 9,
            "entity": "system",
            "start": 3,
            "value": "基础资源平台"
          }
        ],
        "intent": "get_people_in_system",
        "text": "告诉我基础资源平台负责人是哪位呢"
      },
      {
        "entities": [
          {
            "end": 17,
            "entity": "system",
            "start": 3,
            "value": "管理部一体化在线政务服务平台"
          }
        ],
        "intent": "get_people_in_system",
        "text": "告诉我管理部一体化在线政务服务平台联系者"
      },
      {
        "entities": [
          {
            "end": 12,
            "entity": "system",
            "start": 3,
            "value": "运维管理大数据平台"
          }
        ],
        "intent": "get_people_in_system",
        "text": "告诉我运维管理大数据平台主管者是哪位"
      },
      {
        "entities": [
          {
            "end": 12,
            "entity": "system",
            "start": 3,
            "value": "运维管理大数据平台"
          }
        ],
        "intent": "get_people_in_system",
        "text": "告诉我运维管理大数据平台的主管人是谁呢"
      },
      {
        "entities": [
          {
            "end": 12,
            "entity": "system",
            "start": 3,
            "value": "运维管理大数据平台"
          }
        ],
        "intent": "get_people_in_system",
        "text": "告诉我运维管理大数据平台的联系者是哪位呢"
      },
      {
        "entities": [
          {
            "end": 12,
            "entity": "system",
            "start": 3,
            "value": "运维管理大数据平台"
          }
        ],
        "intent": "get_people_in_system",
        "text": "告诉我运维管理大数据平台的负责者"
      },
      {
        "entities": [
          {
            "end": 12,
            "entity": "system",
            "start": 3,
            "value": "运维管理大数据平台"
          }
        ],
        "intent": "get_people_in_system",
        "text": "告诉我运维管理大数据平台联系者是哪位呢"
      },
      {
        "entities": [
          {
            "end": 7,
            "entity": "system",
            "start": 3,
            "value": "这个平台"
          }
        ],
        "intent": "get_people_in_system",
        "text": "告诉我这个平台的主管者"
      },
      {
        "entities": [
          {
            "end": 7,
            "entity": "system",
            "start": 3,
            "value": "这个平台"
          }
        ],
        "intent": "get_people_in_system",
        "text": "告诉我这个平台的联系人是谁"
      },
      {
        "entities": [
          {
            "end": 7,
            "entity": "system",
            "start": 3,
            "value": "这个平台"
          }
        ],
        "intent": "get_people_in_system",
        "text": "告诉我这个平台负责人"
      },
      {
        "entities": [
          {
            "end": 7,
            "entity": "system",
            "start": 3,
            "value": "这个系统"
          }
        ],
        "intent": "get_people_in_system",
        "text": "告诉我这个系统的负责人"
      },
      {
        "entities": [
          {
            "end": 7,
            "entity": "system",
            "start": 3,
            "value": "这个系统"
          }
        ],
        "intent": "get_people_in_system",
        "text": "告诉我这个系统的负责人是哪位"
      },
      {
        "entities": [
          {
            "end": 7,
            "entity": "system",
            "start": 3,
            "value": "这个系统"
          }
        ],
        "intent": "get_people_in_system",
        "text": "告诉我这个系统联系人是谁呢"
      },
      {
        "entities": [
          {
            "end": 11,
            "entity": "system",
            "start": 3,
            "value": "防旱抗旱系统平台"
          }
        ],
        "intent": "get_people_in_system",
        "text": "告诉我防旱抗旱系统平台主管人"
      },
      {
        "entities": [
          {
            "end": 11,
            "entity": "system",
            "start": 3,
            "value": "防旱抗旱系统平台"
          }
        ],
        "intent": "get_people_in_system",
        "text": "告诉我防旱抗旱系统平台的主管人是哪位啊"
      },
      {
        "entities": [
          {
            "end": 6,
            "entity": "system",
            "start": 0,
            "value": "基础资源平台"
          }
        ],
        "intent": "get_people_in_system",
        "text": "基础资源平台主管者"
      },
      {
        "entities": [
          {
            "end": 6,
            "entity": "system",
            "start": 0,
            "value": "基础资源平台"
          }
        ],
        "intent": "get_people_in_system",
        "text": "基础资源平台的主管人是哪位呢"
      },
      {
        "entities": [
          {
            "end": 6,
            "entity": "system",
            "start": 0,
            "value": "基础资源平台"
          }
        ],
        "intent": "get_people_in_system",
        "text": "基础资源平台的主管者"
      },
      {
        "entities": [
          {
            "end": 6,
            "entity": "system",
            "start": 0,
            "value": "基础资源平台"
          }
        ],
        "intent": "get_people_in_system",
        "text": "基础资源平台的联系人"
      },
      {
        "entities": [
          {
            "end": 6,
            "entity": "system",
            "start": 0,
            "value": "基础资源平台"
          }
        ],
        "intent": "get_people_in_system",
        "text": "基础资源平台的联系人是哪位啊"
      },
      {
        "entities": [
          {
            "end": 6,
            "entity": "system",
            "start": 0,
            "value": "基础资源平台"
          }
        ],
        "intent": "get_people_in_system",
        "text": "基础资源平台的联系人是谁呢"
      },
      {
        "entities": [
          {
            "end": 6,
            "entity": "system",
            "start": 0,
            "value": "基础资源平台"
          }
        ],
        "intent": "get_people_in_system",
        "text": "基础资源平台联系人"
      },
      {
        "entities": [
          {
            "end": 14,
            "entity": "system",
            "start": 0,
            "value": "管理部一体化在线政务服务平台"
          }
        ],
        "intent": "get_people_in_system",
        "text": "管理部一体化在线政务服务平台的主管者"
      },
      {
        "entities": [
          {
            "end": 14,
            "entity": "system",
            "start": 0,
            "value": "管理部一体化在线政务服务平台"
          }
        ],
        "intent": "get_people_in_system",
        "text": "管理部一体化在线政务服务平台的联系人"
      },
      {
        "entities": [
          {
            "end": 14,
            "entity": "system",
            "start": 0,
            "value": "管理部一体化在线政务服务平台"
          }
        ],
        "intent": "get_people_in_system",
        "text": "管理部一体化在线政务服务平台的联系者"
      },
      {
        "entities": [
          {
            "end": 14,
            "entity": "system",
            "start": 0,
            "value": "管理部一体化在线政务服务平台"
          }
        ],
        "intent": "get_people_in_system",
        "text": "管理部一体化在线政务服务平台的负责者是哪位呀"
      },
      {
        "entities": [
          {
            "end": 14,
            "entity": "system",
            "start": 0,
            "value": "管理部一体化在线政务服务平台"
          }
        ],
        "intent": "get_people_in_system",
        "text": "管理部一体化在线政务服务平台联系者"
      },
      {
        "entities": [
          {
            "end": 14,
            "entity": "system",
            "start": 0,
            "value": "管理部一体化在线政务服务平台"
          }
        ],
        "intent": "get_people_in_system",
        "text": "管理部一体化在线政务服务平台联系者是谁呢"
      },
      {
        "entities": [
          {
            "end": 14,
            "entity": "system",
            "start": 0,
            "value": "管理部一体化在线政务服务平台"
          }
        ],
        "intent": "get_people_in_system",
        "text": "管理部一体化在线政务服务平台负责人是哪位"
      },
      {
        "entities": [
          {
            "end": 14,
            "entity": "system",
            "start": 0,
            "value": "管理部一体化在线政务服务平台"
          }
        ],
        "intent": "get_people_in_system",
        "text": "管理部一体化在线政务服务平台负责者是谁"
      },
      {
        "entities": [
          {
            "end": 9,
            "entity": "system",
            "start": 2,
            "value": "华为大数据平台"
          }
        ],
        "intent": "get_people_in_system",
        "text": "说下华为大数据平台的联系人"
      },
      {
        "entities": [
          {
            "end": 9,
            "entity": "system",
            "start": 2,
            "value": "华为大数据平台"
          }
        ],
        "intent": "get_people_in_system",
        "text": "说下华为大数据平台联系人是哪位呀"
      },
      {
        "entities": [
          {
            "end": 8,
            "entity": "system",
            "start": 2,
            "value": "基础资源平台"
          }
        ],
        "intent": "get_people_in_system",
        "text": "说下基础资源平台主管者"
      },
      {
        "entities": [
          {
            "end": 8,
            "entity": "system",
            "start": 2,
            "value": "基础资源平台"
          }
        ],
        "intent": "get_people_in_system",
        "text": "说下基础资源平台的主管人是谁呢"
      },
      {
        "entities": [
          {
            "end": 8,
            "entity": "system",
            "start": 2,
            "value": "基础资源平台"
          }
        ],
        "intent": "get_people_in_system",
        "text": "说下基础资源平台的主管者是谁啊"
      },
      {
        "entities": [
          {
            "end": 8,
            "entity": "system",
            "start": 2,
            "value": "基础资源平台"
          }
        ],
        "intent": "get_people_in_system",
        "text": "说下基础资源平台的联系者是哪位啊"
      },
      {
        "entities": [
          {
            "end": 8,
            "entity": "system",
            "start": 2,
            "value": "基础资源平台"
          }
        ],
        "intent": "get_people_in_system",
        "text": "说下基础资源平台的负责者"
      },
      {
        "entities": [
          {
            "end": 8,
            "entity": "system",
            "start": 2,
            "value": "基础资源平台"
          }
        ],
        "intent": "get_people_in_system",
        "text": "说下基础资源平台联系者"
      },
      {
        "entities": [
          {
            "end": 16,
            "entity": "system",
            "start": 2,
            "value": "管理部一体化在线政务服务平台"
          }
        ],
        "intent": "get_people_in_system",
        "text": "说下管理部一体化在线政务服务平台主管人是谁"
      },
      {
        "entities": [
          {
            "end": 16,
            "entity": "system",
            "start": 2,
            "value": "管理部一体化在线政务服务平台"
          }
        ],
        "intent": "get_people_in_system",
        "text": "说下管理部一体化在线政务服务平台的联系者是哪位呢"
      },
      {
        "entities": [
          {
            "end": 16,
            "entity": "system",
            "start": 2,
            "value": "管理部一体化在线政务服务平台"
          }
        ],
        "intent": "get_people_in_system",
        "text": "说下管理部一体化在线政务服务平台的联系者是谁啊"
      },
      {
        "entities": [
          {
            "end": 11,
            "entity": "system",
            "start": 2,
            "value": "运维管理大数据平台"
          }
        ],
        "intent": "get_people_in_system",
        "text": "说下运维管理大数据平台的主管者"
      },
      {
        "entities": [
          {
            "end": 11,
            "entity": "system",
            "start": 2,
            "value": "运维管理大数据平台"
          }
        ],
        "intent": "get_people_in_system",
        "text": "说下运维管理大数据平台的联系者"
      },
      {
        "entities": [
          {
            "end": 11,
            "entity": "system",
            "start": 2,
            "value": "运维管理大数据平台"
          }
        ],
        "intent": "get_people_in_system",
        "text": "说下运维管理大数据平台联系人是哪位"
      },
      {
        "entities": [
          {
            "end": 11,
            "entity": "system",
            "start": 2,
            "value": "运维管理大数据平台"
          }
        ],
        "intent": "get_people_in_system",
        "text": "说下运维管理大数据平台联系者"
      },
      {
        "entities": [
          {
            "end": 11,
            "entity": "system",
            "start": 2,
            "value": "运维管理大数据平台"
          }
        ],
        "intent": "get_people_in_system",
        "text": "说下运维管理大数据平台负责人是哪位"
      },
      {
        "entities": [
          {
            "end": 6,
            "entity": "system",
            "start": 2,
            "value": "这个系统"
          }
        ],
        "intent": "get_people_in_system",
        "text": "说下这个系统的负责者"
      },
      {
        "entities": [
          {
            "end": 6,
            "entity": "system",
            "start": 2,
            "value": "这个系统"
          }
        ],
        "intent": "get_people_in_system",
        "text": "说下这个系统负责人是谁"
      },
      {
        "entities": [
          {
            "end": 10,
            "entity": "system",
            "start": 2,
            "value": "防旱抗旱系统平台"
          }
        ],
        "intent": "get_people_in_system",
        "text": "说下防旱抗旱系统平台的主管人"
      },
      {
        "entities": [
          {
            "end": 10,
            "entity": "system",
            "start": 2,
            "value": "防旱抗旱系统平台"
          }
        ],
        "intent": "get_people_in_system",
        "text": "说下防旱抗旱系统平台负责人"
      },
      {
        "entities": [
          {
            "end": 9,
            "entity": "system",
            "start": 0,
            "value": "运维管理大数据平台"
          }
        ],
        "intent": "get_people_in_system",
        "text": "运维管理大数据平台主管人"
      },
      {
        "entities": [
          {
            "end": 9,
            "entity": "system",
            "start": 0,
            "value": "运维管理大数据平台"
          }
        ],
        "intent": "get_people_in_system",
        "text": "运维管理大数据平台主管人是谁"
      },
      {
        "entities": [
          {
            "end": 9,
            "entity": "system",
            "start": 0,
            "value": "运维管理大数据平台"
          }
        ],
        "intent": "get_people_in_system",
        "text": "运维管理大数据平台主管者是哪位"
      },
      {
        "entities": [
          {
            "end": 9,
            "entity": "system",
            "start": 0,
            "value": "运维管理大数据平台"
          }
        ],
        "intent": "get_people_in_system",
        "text": "运维管理大数据平台的主管人"
      },
      {
        "entities": [
          {
            "end": 9,
            "entity": "system",
            "start": 0,
            "value": "运维管理大数据平台"
          }
        ],
        "intent": "get_people_in_system",
        "text": "运维管理大数据平台的主管人是哪位"
      },
      {
        "entities": [
          {
            "end": 9,
            "entity": "system",
            "start": 0,
            "value": "运维管理大数据平台"
          }
        ],
        "intent": "get_people_in_system",
        "text": "运维管理大数据平台的主管者"
      },
      {
        "entities": [
          {
            "end": 9,
            "entity": "system",
            "start": 0,
            "value": "运维管理大数据平台"
          }
        ],
        "intent": "get_people_in_system",
        "text": "运维管理大数据平台的负责人"
      },
      {
        "entities": [
          {
            "end": 9,
            "entity": "system",
            "start": 0,
            "value": "运维管理大数据平台"
          }
        ],
        "intent": "get_people_in_system",
        "text": "运维管理大数据平台的负责者"
      },
      {
        "entities": [
          {
            "end": 9,
            "entity": "system",
            "start": 0,
            "value": "运维管理大数据平台"
          }
        ],
        "intent": "get_people_in_system",
        "text": "运维管理大数据平台联系人"
      },
      {
        "entities": [
          {
            "end": 9,
            "entity": "system",
            "start": 0,
            "value": "运维管理大数据平台"
          }
        ],
        "intent": "get_people_in_system",
        "text": "运维管理大数据平台联系人是谁呢"
      },
      {
        "entities": [
          {
            "end": 9,
            "entity": "system",
            "start": 0,
            "value": "运维管理大数据平台"
          }
        ],
        "intent": "get_people_in_system",
        "text": "运维管理大数据平台联系者是哪位"
      },
      {
        "entities": [
          {
            "end": 9,
            "entity": "system",
            "start": 0,
            "value": "运维管理大数据平台"
          }
        ],
        "intent": "get_people_in_system",
        "text": "运维管理大数据平台负责人"
      },
      {
        "entities": [
          {
            "end": 9,
            "entity": "system",
            "start": 0,
            "value": "运维管理大数据平台"
          }
        ],
        "intent": "get_people_in_system",
        "text": "运维管理大数据平台负责人是哪位啊"
      },
      {
        "entities": [
          {
            "end": 4,
            "entity": "system",
            "start": 0,
            "value": "这个平台"
          }
        ],
        "intent": "get_people_in_system",
        "text": "这个平台主管人是谁呀"
      },
      {
        "entities": [
          {
            "end": 4,
            "entity": "system",
            "start": 0,
            "value": "这个平台"
          }
        ],
        "intent": "get_people_in_system",
        "text": "这个平台主管者是谁呀"
      },
      {
        "entities": [
          {
            "end": 4,
            "entity": "system",
            "start": 0,
            "value": "这个平台"
          }
        ],
        "intent": "get_people_in_system",
        "text": "这个平台主管者是谁啊"
      },
      {
        "entities": [
          {
            "end": 4,
            "entity": "system",
            "start": 0,
            "value": "这个平台"
          }
        ],
        "intent": "get_people_in_system",
        "text": "这个平台的主管人是谁呢"
      },
      {
        "entities": [
          {
            "end": 4,
            "entity": "system",
            "start": 0,
            "value": "这个平台"
          }
        ],
        "intent": "get_people_in_system",
        "text": "这个平台的主管者是哪位"
      },
      {
        "entities": [
          {
            "end": 4,
            "entity": "system",
            "start": 0,
            "value": "这个平台"
          }
        ],
        "intent": "get_people_in_system",
        "text": "这个平台负责人是谁"
      },
      {
        "entities": [
          {
            "end": 4,
            "entity": "system",
            "start": 0,
            "value": "这个平台"
          }
        ],
        "intent": "get_people_in_system",
        "text": "这个平台负责者"
      },
      {
        "entities": [
          {
            "end": 4,
            "entity": "system",
            "start": 0,
            "value": "这个系统"
          }
        ],
        "intent": "get_people_in_system",
        "text": "这个系统主管者"
      },
      {
        "entities": [
          {
            "end": 4,
            "entity": "system",
            "start": 0,
            "value": "这个系统"
          }
        ],
        "intent": "get_people_in_system",
        "text": "这个系统主管者是哪位"
      },
      {
        "entities": [
          {
            "end": 4,
            "entity": "system",
            "start": 0,
            "value": "这个系统"
          }
        ],
        "intent": "get_people_in_system",
        "text": "这个系统的主管人是谁"
      },
      {
        "entities": [
          {
            "end": 4,
            "entity": "system",
            "start": 0,
            "value": "这个系统"
          }
        ],
        "intent": "get_people_in_system",
        "text": "这个系统的主管人是谁啊"
      },
      {
        "entities": [
          {
            "end": 4,
            "entity": "system",
            "start": 0,
            "value": "这个系统"
          }
        ],
        "intent": "get_people_in_system",
        "text": "这个系统的主管者"
      },
      {
        "entities": [
          {
            "end": 4,
            "entity": "system",
            "start": 0,
            "value": "这个系统"
          }
        ],
        "intent": "get_people_in_system",
        "text": "这个系统的负责人"
      },
      {
        "entities": [
          {
            "end": 4,
            "entity": "system",
            "start": 0,
            "value": "这个系统"
          }
        ],
        "intent": "get_people_in_system",
        "text": "这个系统联系人是谁呀"
      },
      {
        "entities": [
          {
            "end": 4,
            "entity": "system",
            "start": 0,
            "value": "这个系统"
          }
        ],
        "intent": "get_people_in_system",
        "text": "这个系统负责人"
      },
      {
        "entities": [
          {
            "end": 4,
            "entity": "system",
            "start": 0,
            "value": "这个系统"
          }
        ],
        "intent": "get_people_in_system",
        "text": "这个系统负责人是谁呢"
      },
      {
        "entities": [
          {
            "end": 8,
            "entity": "system",
            "start": 0,
            "value": "防旱抗旱系统平台"
          }
        ],
        "intent": "get_people_in_system",
        "text": "防旱抗旱系统平台主管者"
      },
      {
        "entities": [
          {
            "end": 8,
            "entity": "system",
            "start": 0,
            "value": "防旱抗旱系统平台"
          }
        ],
        "intent": "get_people_in_system",
        "text": "防旱抗旱系统平台主管者是哪位"
      },
      {
        "entities": [
          {
            "end": 8,
            "entity": "system",
            "start": 0,
            "value": "防旱抗旱系统平台"
          }
        ],
        "intent": "get_people_in_system",
        "text": "防旱抗旱系统平台的主管者"
      },
      {
        "entities": [
          {
            "end": 8,
            "entity": "system",
            "start": 0,
            "value": "防旱抗旱系统平台"
          }
        ],
        "intent": "get_people_in_system",
        "text": "防旱抗旱系统平台的联系人"
      },
      {
        "entities": [
          {
            "end": 8,
            "entity": "system",
            "start": 0,
            "value": "防旱抗旱系统平台"
          }
        ],
        "intent": "get_people_in_system",
        "text": "防旱抗旱系统平台的联系者"
      },
      {
        "entities": [
          {
            "end": 8,
            "entity": "system",
            "start": 0,
            "value": "防旱抗旱系统平台"
          }
        ],
        "intent": "get_people_in_system",
        "text": "防旱抗旱系统平台的负责人"
      },
      {
        "entities": [
          {
            "end": 8,
            "entity": "system",
            "start": 0,
            "value": "防旱抗旱系统平台"
          }
        ],
        "intent": "get_people_in_system",
        "text": "防旱抗旱系统平台的负责者"
      },
      {
        "entities": [
          {
            "end": 8,
            "entity": "system",
            "start": 0,
            "value": "防旱抗旱系统平台"
          }
        ],
        "intent": "get_people_in_system",
        "text": "防旱抗旱系统平台的负责者是谁呢"
      },
      {
        "entities": [
          {
            "end": 8,
            "entity": "system",
            "start": 0,
            "value": "防旱抗旱系统平台"
          }
        ],
        "intent": "get_people_in_system",
        "text": "防旱抗旱系统平台联系人是谁"
      },
      {
        "entities": [
          {
            "end": 8,
            "entity": "system",
            "start": 0,
            "value": "防旱抗旱系统平台"
          }
        ],
        "intent": "get_people_in_system",
        "text": "防旱抗旱系统平台联系者"
      },
      {
        "entities": [
          {
            "end": 8,
            "entity": "system",
            "start": 0,
            "value": "防旱抗旱系统平台"
          }
        ],
        "intent": "get_people_in_system",
        "text": "防旱抗旱系统平台负责者是谁呀"
      }
    ],
    "entity_synonyms": [],
    "lookup_tables": [],
    "regex_features": []
  }
}